blazingmq-1.2.2.dist-info/METADATA
blazingmq-1.2.2.dist-info/RECORD
blazingmq-1.2.2.dist-info/top_level.txt
blazingmq-1.2.2.dist-info/WHEEL
blazingmq-1.2.2.dist-info/LICENSE
blazingmq/exceptions.py
blazingmq/_typing.py
blazingmq/_messages.py
blazingmq/py.typed
blazingmq/_ext.cpython-312-x86_64-linux-gnu.so
blazingmq/_script_name.py
blazingmq/__init__.py
blazingmq/_enums.py
blazingmq/_ext.pyi
blazingmq/_about.py
blazingmq/_timeouts.py
blazingmq/_monitors.py
blazingmq/_six.py
blazingmq/testing.py
blazingmq/session_events.py
blazingmq/_session.py
blazingmq/_callbacks.py
